dc43/__init__.py
dc43/odcs.py
dc43/versioning.py
dc43/core/__init__.py
dc43/core/odcs.py
dc43/core/odps.py
dc43/core/versioning.py
dc43-0.27.0.0.dist-info/licenses/LICENSE
dc43-0.27.0.0.dist-info/METADATA
dc43-0.27.0.0.dist-info/WHEEL
dc43-0.27.0.0.dist-info/top_level.txt
dc43-0.27.0.0.dist-info/RECORD
