Metadata-Version: 2.4
Name: dc43
Version: 0.27.0.0
Summary: Data contracts For Free using ODCS (Bitol)
Author: Andy Petrella
Classifier: Programming Language :: Python :: 3
Classifier: License :: OSI Approved :: MIT License
Classifier: Operating System :: OS Independent
Requires-Python: >=3.11
License-File: LICENSE
Requires-Dist: dc43-core>=0.27.0.0rc0
Requires-Dist: dc43-service-clients>=0.27.0.0rc0
Requires-Dist: dc43-service-backends>=0.27.0.0rc0
Requires-Dist: dc43-integrations>=0.27.0.0rc0
Requires-Dist: dc43-contracts-app>=0.27.0.0rc0
Requires-Dist: packaging>=21.0
Requires-Dist: open-data-contract-standard==3.0.2
Provides-Extra: spark
Requires-Dist: dc43-integrations[spark]>=0.27.0.0rc0; extra == "spark"
Provides-Extra: docs-chat
Requires-Dist: dc43-contracts-app[docs-chat]>=0.27.0.0rc0; extra == "docs-chat"
Provides-Extra: test
Requires-Dist: pytest>=7.0; extra == "test"
Requires-Dist: pyspark>=3.4; extra == "test"
Requires-Dist: fastapi; extra == "test"
Requires-Dist: jinja2; extra == "test"
Requires-Dist: python-multipart; extra == "test"
Requires-Dist: httpx; extra == "test"
Requires-Dist: dc43-contracts-app[spark]>=0.27.0.0rc0; extra == "test"
Provides-Extra: demo
Requires-Dist: fastapi; extra == "demo"
Requires-Dist: uvicorn; extra == "demo"
Requires-Dist: jinja2; extra == "demo"
Requires-Dist: python-multipart; extra == "demo"
Requires-Dist: dc43-contracts-app[docs-chat,spark]>=0.27.0.0rc0; extra == "demo"
Requires-Dist: dc43-integrations[spark]>=0.27.0.0rc0; extra == "demo"
Requires-Dist: dc43-demo-app>=0.27.0.0rc0; extra == "demo"
Dynamic: license-file
Dynamic: provides-extra
Dynamic: requires-dist
